all_packages/__main__.py
all_packages/version.py
all_packages-1.0.1.dist-info/LICENSE
all_packages-1.0.1.dist-info/METADATA
all_packages-1.0.1.dist-info/WHEEL
all_packages-1.0.1.dist-info/entry_points.txt
all_packages-1.0.1.dist-info/top_level.txt
all_packages-1.0.1.dist-info/RECORD
