Metadata-Version: 2.1
Name: all-packages
Version: 1.0.1
Summary: Install every package on PyPI
Home-page: https://github.com/adang1345/all_packages
Author: Aohan Dang
Author-email: adang1345@gmail.com
License: MIT
Platform: UNKNOWN
Classifier: License :: OSI Approved :: MIT License
Requires-Python: >=3.6
